vimtool/__init__.py
vimtool/cli.py
vimtool/compatibility.py
vimtool/core.py
vimtool/environment.py
vimtool/handle_buffer.py
vimtool/position.py
vimtool/todos.py
vimtool/vim_helper.py
vimtool/vimtool_manager.py
vimtool/db/__init__.py
vimtool/db/dal.py
vimstrument-0.0.1.dist-info/METADATA
vimstrument-0.0.1.dist-info/WHEEL
vimstrument-0.0.1.dist-info/entry_points.txt
vimstrument-0.0.1.dist-info/top_level.txt
vimstrument-0.0.1.dist-info/RECORD
