Metadata-Version: 2.1
Name: vimstrument
Version: 0.0.1
Summary: "todo manager with VIM integration"
Home-page: https://github.com/sysid/twbm
Author: sysid
Author-email: sysid@gmx.de
License: UNKNOWN
Platform: UNKNOWN
Classifier: Development Status :: 4 - Beta
Classifier: Environment :: Console
Classifier: Intended Audience :: Developers
Classifier: License :: OSI Approved :: GNU General Public License v3 (GPLv3)
Classifier: Operating System :: OS Independent
Classifier: Topic :: Utilities
Classifier: Programming Language :: Python :: 3
Classifier: Programming Language :: Python :: 3.9
Requires-Python: >=3.9
Requires-Dist: aiosql
Requires-Dist: SQLAlchemy
Requires-Dist: alembic
Requires-Dist: typer
Requires-Dist: pydantic[dotenv]
